Workbook

Sheet Sum-Calculation
F2: Expenditure Against Project | M2: Cah In Hand
C3: Clinet End | I3: Expenditure & Received Amount
A4: Sl | B4: Description | C4: PO Amount | D4: Advance Amount | E4: Collection Due from client | F4: OEM/Vandor Payment | G4: Speed Money | H4: Salary and Conveyance | I4: Project Local Expenditure | J4: Local Conveyance | K4: Official Expenditure | L4: Hand cash sharmin
A5: 1 | B5: All Project | C5: ='Client & PO'!C11 -> 0 | D5: ='Client & PO'!D11+'Client & PO'!E11 -> 0 | E5: ='Client & PO'!G11 -> 0 | F5: ='SNS Issue PO & Expenditure (2)'!E20 -> 0 | G5: =SE!D9 -> 0 | H5: ='Salary and Conveyance'!E32 -> 0 | I5: ='Expenditure & Received Amount '!#REF! -> #REF!
M8: =M5-M7 -> 0

Sheet BCBL-Summary
A1: 05.03.2025(BCBL AC Calculation)
A2: Client Received Amount -BCBL | E2: Cost Calculation
A3: SL. | B3: Received Date | C3: Description | D3: Received Amount | E3: SL. | F3: Date | G3: Project Name | H3: Description | I3: Paid Amount | J3: Remarks
A6: Total Received Amount From Client | D6: =SUM(D4:D5) -> 0 | H6: Total Received from DBBL/MD Sir | I6: =SUM(I4:I5) -> 0
A7: Total Costing Amount | D7: =I6 -> 0 | H7: Cash Received from Vendor /Sharmin
A8: Remaining in DBBL Account | D8: =D6-D7 -> 0 | H8: Total Received
A9: SNS er Account e Chilo
A10: Remaining in DBBL Account-SNS er Account e Chilo | D10: =D8+D9 -> 0
A14: Client Received Amount -NRBC-MWT Informatics Limited | E14: Cost Calculation
A15: SL. | B15: Received Date | C15: Description | D15: Received Amount | E15: SL. | F15: Date | G15: Project Name | H15: Description | I15: Paid Amount | J15: Remarks
A20: Total Received Amount From BCBL | D20: =SUM(D17:D19) -> 0 | H20: Total Costing from NRBC/MD Sir | I20: =SUM(I16:I19) -> 0
A21: Total Costing Amount | D21: =I20 -> 0 | H21: Cash Received from Vendor /Sharmin
A22: Remaining in NRBC Account | D22: =D20-D21 -> 0 | H22: Total Received
A24: 12.08.2025(EBL AC Calculation)
A25: Client Received Amount -EBL-MWTIL | E25: Cost Calculation
A26: SL. | B26: Received Date | C26: Description | D26: Received Amount | E26: SL. | F26: Date | G26: Project Name | H26: Description | I26: Paid Amount | J26: Remarks
A29: Total Received Amount From BCBL | D29: =SUM(D26:D28) -> 0 | H29: Total Costing from NRBC/MD Sir | I29: =SUM(I25:I28) -> 0
A30: Total Costing Amount | D30: =I29 -> 0 | H30: Cash Received from Vendor /Sharmin
A31: Remaining in NRBC Account | D31: =D29-D30 -> 0 | H31: Total Received
A33: 12.08.2025(EBL AC Calculation)
A34: Client Received Amount -DBBL-MWTIL | E34: Cost Calculation
A35: SL. | B35: Received Date | C35: Description | D35: Received Amount | E35: SL. | F35: Date | G35: Project Name | H35: Description | I35: Paid Amount | J35: Remarks
A42: Total Received Amount From BCBL | D42: =SUM(D35:D37) -> 0 | H42: Total Costing from DBBL/MD Sir | I42: =SUM(I34:I37) -> 0
A43: Total Costing Amount | D43: =I42 -> 0 | H43: Cash Received from Vendor /Sharmin
A44: Remaining in NRBC Account | D44: =D42-D43 -> 0 | H44: Total Received

Sheet Client & PO
A3: Vender Name & PO Amount
D4: Advance Received | G4: Remaining Due
A5: SL | B5: Client Name | C5: PO Value | D5: AC Pay | E5: Hand Cash | F5: Date-PO | G5: Due | H5: Payment Date | I5: Remarks
B11: Total Amount | C11: =SUM(C6:C9) -> 0 | D11: =SUM(D6:D10) -> 0 | E11: =SUM(E6:E10) -> 0 | G11: =SUM(C11-D11-E11) -> 0
A12: Total Advance Received | D12: =D11+E11 -> 0

Sheet SNS Issue PO & Expenditure (2)
E2: Vendor Payment | G2: Nobabpur & Others
A3: SL | B3: Project Name | C3: Purchase Vendor Name | D3: PO | E3: A/C Pay(BCBL) | F3: Cash Payment | G3: Local Purchase | H3: Payment Due | I3: PO Pending | J3: Local Purchase | K3: Delivery | L3: Delivey Challan | M3: Delivery Date | N3: WCR | O3: Warrenty | P3: Remarks
A20: Sub-Total | D20: =SUM(D4:D9) -> 0 | E20: =SUM(E4:E9) -> 0 | F20: =SUM(F4:F9) -> 0 | H20: =SUM(H4:H9) -> 0
A21: Grand Total -Purchase | D21: =E20+F20+G20+H20 -> 0
C34: 3.5
C45: 4.07 | D45: 4 | E45: =D45/C45 -> 0.98280098
E47: 3
C49: 4.5 | D49: =D45/C49 -> 0.88888889 | E49: =D45/E47 -> 1.3333333

Sheet SE
A4: SL | B4: Project Name | C4: Description | D4: Costing Amount | E4: Payment (BCBL) | F4: Cash Payment | G4: Payment Due | H4: Remarks
A5: 1 | G5: =D5-E5-F5 -> 0
A6: 2 | G6: =D6-E6 -> 0
D9: =SUM(D5:D8) -> 0 | E9: =SUM(E5:E8) -> 0 | F9: =SUM(F5:F8) -> 0 | G9: =SUM(G5:G8) -> 0

Sheet Salary and Conveyance
A2: Monthly Fixed Cost from - Jan'2026
A3: Sl | B3: Expenditure | C3: Month | D3: Unit Price | E3: Total Cost | F3: Remark's
A4: A | B4: SNS Salary
A6: 1
A7: 1
A10: SNS Salary for the Month of Jan'26(A) | E10: =SUM(E5:E9) -> 0
A11: B | B11: SNS-Official Expenditure
A12: 1 | B12: Office Rent (50%, 40000) | C12: 1 | D12: 0 | E12: =C12*D12 -> 0
A13: 2 | B13: Electric Bill (50%,15000) | C13: 1 | D13: 0 | E13: =C13*D13 -> 0
A14: 3 | B14: Wifi Bill (50%,1800) | C14: 1 | D14: 0 | E14: =C14*D14 -> 0
A15: 4 | B15: Water + GAS (50%) | C15: 1 | D15: 0 | E15: =C15*D15 -> 0
A16: 5 | B16: Warehouse Rent+Utility+Stair Clean | C16: 1 | D16: 0 | E16: =C16*D16 -> 0
A17: 6 | B17: Ware House(Wifi bill) April'24 | C17: 1 | D17: 0 | E17: =C17*D17 -> 0
A18: 7 | B18: Others official expenditure(Monthly VAT,Transgender,Papers,PAD,entertain etc.) | C18: 1 | D18: 0 | E18: =C18*D18 -> 0
A19: 10 | B19: TVNL -Power Module Purchase/EX
A20: Total-SNS-Official Expenditure (B) | E20: =SUM(E11:E19) -> 0
A21: C | B21: SNS-Conveyance
A22: 1 | B22: Conveyance For the month of March'24 | C22: 1
A23: 2 | B23: (Conveyance for the month of Mar'25) | C23: 1
A24: 3 | C24: 1
A25: 4 | C25: 1
A26: 5 | C26: 1
A27: 6 | C27: 1
A28: 7 | C28: 1
A29: 8 | C29: 1
A31: Total-SNS Conveyance (C) | E31: =SUM(E22:E30) -> 0
A32: Total Expenditure (A+B+C) | E32: =E31+E10+E20 -> 0
B33: N.B: SNS will paid above expenditure each month before date 5
B37: Conveyance Nov/24
A38: Sl | B38: Name | C38: Amount
A39: 2 | B39: (Conveyance for the month of Mar'25)
A40: Total | C40: =SUM(C39:C39) -> 0

Sheet Expenditure & Received Amount 
A2: Received Amount | E2: (Project costing Calculation)SNS
A3: SL | B3: Received Date | C3: Received Name | D3: Received Amount | E3: SL | F3: office Expenditure | G3: UOM | H3: Qty. | I3: Paid Amount | J3: Total Amount | K3: Project Local Expenditure | L3: Conveyance | M3: office Expenditure | N3: Remark's
F16: Total Costing Amount | G16: =SUM(G4:G15) -> 0
F17: Total Received Amount | G17: =D8 -> 0
F18: Remaining In Hand | G18: =G17-G16 -> 0

Sheet Local Purchase
B4: Project Wase Local Purchases
A5: SL | B5: Projecct Name | C5: Date | D5: Description | E5: Recugation Amount | F5: Paid Amount-SNS | G5: Paid Amount-MWTIL | H5: Petty cash | I5: Due Amount | J5: Total Costing Amount
I17: =E17-F17-G17-H17 -> 0
E18: =SUM(E6:E17) -> 0 | F18: =SUM(F6:F17) -> 0 | G18: =SUM(G6:G17) -> 0 | H18: =SUM(H6:H17) -> 0 | I18: =SUM(I6:I17) -> 0

Sheet Conveyance
A4: SNS Global Expenses
A5: SL | B5: office Expenditure | C5: Costing Amount | D5: Paid Amount | E5: Remark's | F5: Received Date | G5: Received Name | H5: Received Amount
B29: SNS Global Expenses Total Expenses | D29: =SUM(D6:D25) -> 0 | H29: =H7+H8+H9+H10+H11+H12+H13+H14+H15+H16+H17+H18+H19+H20+H21+H22+H23+H24+H25 -> 0
B30: SNS Global Limited (B)
A31: Remaining In Hand/Due Amount | D31: =H29-D29 -> 0
